aiandml/Tips.csv
aiandml/__init__.py
aiandml/a_star.py
aiandml/ao_star.py
aiandml/back_propagation.png
aiandml/back_propagation.py
aiandml/back_propagation2.jpg
aiandml/candidate_elimination.py
aiandml/candidate_elimination_algo.png
aiandml/data3.csv
aiandml/data3_test.csv
aiandml/em_and_k_means.png
aiandml/em_and_k_means.py
aiandml/gfg.jpg
aiandml/id3.jpg
aiandml/id3.py
aiandml/k_nearest.png
aiandml/k_nearest.py
aiandml/locally_weighted_regression.png
aiandml/locally_weighted_regression.py
aiandml/naive_bayesian_classifier.png
aiandml/naive_bayesian_classifier.py
aiandml/pima-indians-diabetes.csv
aiandml/pima_indian.csv
aiandml/play_tennis.csv
aiandml/ws.csv
aiandml-1.0.6.dist-info/LICENCE.txt
aiandml-1.0.6.dist-info/METADATA
aiandml-1.0.6.dist-info/WHEEL
aiandml-1.0.6.dist-info/top_level.txt
aiandml-1.0.6.dist-info/RECORD
