Metadata-Version: 2.1
Name: aiandml
Version: 1.0.6
Summary: The description of the package   
Author: Ashlesh M D
Author-email: ashleshmd@gmail.com
License: UNKNOWN
Platform: UNKNOWN
Classifier: License :: OSI Approved :: MIT License
Classifier: Programming Language :: Python :: 3
Classifier: Programming Language :: Python :: 3.8
Classifier: License :: OSI Approved :: MIT License
Classifier: Operating System :: OS Independent
Requires-Python: >=3.6
License-File: LICENCE.txt
